lesscli/__init__.py
lesscli/cli.py
lesscli/util.py
lesscli-0.3.0.dist-info/METADATA
lesscli-0.3.0.dist-info/WHEEL
lesscli-0.3.0.dist-info/entry_points.txt
lesscli-0.3.0.dist-info/top_level.txt
lesscli-0.3.0.dist-info/RECORD
